windpyutils/__init__.py
windpyutils/args.py
windpyutils/buffers.py
windpyutils/class_utils.py
windpyutils/config.py
windpyutils/design_patterns.py
windpyutils/files.py
windpyutils/generic.py
windpyutils/logger.py
windpyutils/metrics.py
windpyutils/mocking.py
windpyutils/strings.py
windpyutils/typing.py
windpyutils/parallel/__init__.py
windpyutils/parallel/maps.py
windpyutils/parallel/own_proc_pools.py
windpyutils/parallel/pools.py
windpyutils/parallel/storage.py
windpyutils/parallel/workers.py
windpyutils/structures/__init__.py
windpyutils/structures/caches.py
windpyutils/structures/circular_buffer.py
windpyutils/structures/data_classes.py
windpyutils/structures/lists.py
windpyutils/structures/maps.py
windpyutils/structures/sorted.py
windpyutils/structures/span_set.py
windpyutils/visual/__init__.py
windpyutils/visual/text.py
windpyutils-2.0.49.dist-info/licenses/LICENSE
windpyutils-2.0.49.dist-info/METADATA
windpyutils-2.0.49.dist-info/WHEEL
windpyutils-2.0.49.dist-info/top_level.txt
windpyutils-2.0.49.dist-info/RECORD
