Metadata-Version: 2.4
Name: windpyutils
Version: 2.0.49
Summary: Useful tools for Python projects.
Home-page: https://github.com/mdocekal/windPyUtils
Author: Martin Dočekal
License: The Unlicense
Keywords: utils,general usage
Requires-Python: >=3.7
License-File: LICENSE
Dynamic: author
Dynamic: description
Dynamic: description-content-type
Dynamic: home-page
Dynamic: keywords
Dynamic: license
Dynamic: license-file
Dynamic: requires-python
Dynamic: summary
